[
  {
    "id": "kpi-total-rate",
    "title": "Total Spend Rate",
    "description": "Current USD per hour across monitored resources",
    "position": {
      "h": 2,
      "nextX": 6,
      "nextY": 2,
      "w": 6,
      "x": 0,
      "y": 0
    },
    "viz_type": "chart",
    "viz_content": "SELECT total_hourly_usd FROM aws_cost.aws_cost_1m WHERE _tp_time > now()-1m",
    "viz_config": {
      "chartType": "singleValue",
      "config": {
        "field": "total_hourly_usd",
        "fontSize": 48,
        "fractionDigits": 2,
        "thresholds": [],
        "unit": {
          "position": "left",
          "value": "$"
        }
      }
    }
  },
  {
    "id": "kpi-monthly-proj",
    "title": "Monthly Projection",
    "description": "Current hourly rate × 730 hours",
    "position": {
      "h": 2,
      "nextX": 12,
      "nextY": 2,
      "w": 6,
      "x": 6,
      "y": 0
    },
    "viz_type": "chart",
    "viz_content": "SELECT total_hourly_usd * 730 AS monthly_usd FROM aws_cost.aws_cost_1m WHERE _tp_time > now()-1m",
    "viz_config": {
      "chartType": "singleValue",
      "config": {
        "field": "monthly_usd",
        "fontSize": 48,
        "fractionDigits": 0,
        "thresholds": [],
        "unit": {
          "position": "left",
          "value": "$"
        }
      }
    }
  },
  {
    "id": "chart-cost-time",
    "title": "Hourly Cost Over Time",
    "description": "1-minute samples of total spend rate (USD/hr)",
    "position": {
      "h": 4,
      "nextX": 12,
      "nextY": 6,
      "w": 12,
      "x": 0,
      "y": 2
    },
    "viz_type": "chart",
    "viz_content": "SELECT time, total_hourly_usd FROM aws_cost.aws_cost_1m WHERE _tp_time > now() - 24h",
    "viz_config": {
      "chartType": "line",
      "config": {
        "colors": [
          "#D53F8C"
        ],
        "gridlines": true,
        "legend": false,
        "lineStyle": "curve",
        "xAxis": "time",
        "xRange": "Infinity",
        "yAxis": "total_hourly_usd",
        "yRange": {
          "max": null,
          "min": 0
        }
      }
    }
  },
  {
    "id": "chart-by-service-region",
    "title": "Cost by Service × Region",
    "description": "Hourly USD grouped by service and region (latest cycle)",
    "position": {
      "h": 4,
      "nextX": 6,
      "nextY": 10,
      "w": 6,
      "x": 0,
      "y": 6
    },
    "viz_type": "chart",
    "viz_content": "SELECT service, region, hourly_usd FROM aws_cost.v_cost_by_service_region",
    "viz_config": {
      "chartType": "bar",
      "config": {
        "color": "region",
        "colors": [
          "#D53F8C",
          "#9F2BC0",
          "#F7775A",
          "#F0BE3E",
          "#8934D9",
          "#DA4B36"
        ],
        "dataLabel": false,
        "fractionDigits": 2,
        "gridlines": true,
        "groupType": "dodge",
        "legend": true,
        "unit": {},
        "updateKey": "service",
        "updateMode": "key",
        "xAxis": "service",
        "xTickLabel": {},
        "yAxis": "hourly_usd",
        "yTickLabel": {}
      }
    }
  },
  {
    "id": "chart-by-creator",
    "title": "Cost by Creator",
    "description": "Who is currently spending money (latest cycle)",
    "position": {
      "h": 4,
      "nextX": 12,
      "nextY": 10,
      "w": 6,
      "x": 6,
      "y": 6
    },
    "viz_type": "chart",
    "viz_content": "SELECT creator, hourly_usd FROM aws_cost.v_cost_by_creator ORDER BY hourly_usd DESC LIMIT 15",
    "viz_config": {
      "chartType": "bar",
      "config": {
        "colors": [
          "#9F2BC0"
        ],
        "dataLabel": false,
        "fractionDigits": 2,
        "gridlines": true,
        "unit": {},
        "xAxis": "creator",
        "xTickLabel": {},
        "yAxis": "hourly_usd",
        "yTickLabel": {}
      }
    }
  },
  {
    "id": "table-top-resources",
    "title": "Top 20 Expensive Resources",
    "description": "Resources sorted by hourly cost (latest cycle)",
    "position": {
      "h": 6,
      "nextX": 12,
      "nextY": 16,
      "w": 12,
      "x": 0,
      "y": 10
    },
    "viz_type": "chart",
    "viz_content": "SELECT time, resource_id, service, region, resource_type, creator, hourly_cost_usd, monthly_cost_usd FROM aws_cost.v_top_expensive",
    "viz_config": {
      "chartType": "table",
      "config": {
        "rowCount": 20,
        "tableStyles": {
          "creator": {
            "conditions": [],
            "decreaseColor": "red",
            "highlightRow": false,
            "increaseColor": "green",
            "miniChartType": "",
            "name": "",
            "show": true,
            "trend": false,
            "width": 200
          },
          "hourly_cost_usd": {
            "conditions": [],
            "decreaseColor": "red",
            "highlightRow": false,
            "increaseColor": "green",
            "miniChartType": "",
            "name": "",
            "show": true,
            "trend": false,
            "width": 100
          },
          "monthly_cost_usd": {
            "conditions": [],
            "decreaseColor": "red",
            "highlightRow": false,
            "increaseColor": "green",
            "miniChartType": "",
            "name": "",
            "show": true,
            "trend": false,
            "width": 100
          },
          "region": {
            "conditions": [],
            "decreaseColor": "red",
            "highlightRow": false,
            "increaseColor": "green",
            "miniChartType": "",
            "name": "",
            "show": true,
            "trend": false,
            "width": 200
          },
          "resource_id": {
            "conditions": [],
            "decreaseColor": "red",
            "highlightRow": false,
            "increaseColor": "green",
            "miniChartType": "",
            "name": "",
            "show": true,
            "trend": false,
            "width": 200
          },
          "resource_type": {
            "conditions": [],
            "decreaseColor": "red",
            "highlightRow": false,
            "increaseColor": "green",
            "miniChartType": "",
            "name": "",
            "show": true,
            "trend": false,
            "width": 200
          },
          "service": {
            "conditions": [],
            "decreaseColor": "red",
            "highlightRow": false,
            "increaseColor": "green",
            "miniChartType": "",
            "name": "",
            "show": true,
            "trend": false,
            "width": 200
          },
          "time": {
            "conditions": [],
            "decreaseColor": "red",
            "highlightRow": false,
            "increaseColor": "green",
            "miniChartType": "",
            "name": "",
            "show": false,
            "trend": false,
            "width": 210
          }
        },
        "tableWrap": false,
        "updateKey": "time",
        "updateMode": "time"
      }
    }
  }
]